GraphicalClustering/__int__.py
GraphicalClustering/graph_cluster.py
Graphical_Clustering-0.0.3.dist-info/LICENSE
Graphical_Clustering-0.0.3.dist-info/METADATA
Graphical_Clustering-0.0.3.dist-info/WHEEL
Graphical_Clustering-0.0.3.dist-info/top_level.txt
Graphical_Clustering-0.0.3.dist-info/RECORD
