Metadata-Version: 2.1
Name: Graphical-Clustering
Version: 0.0.3
Summary: Python package to cluster IT support tickets based on its description/resolution remarks
Author-email: Manikandan <nmani.1191@gmail.com>
Project-URL: Homepage, https://github.com/nmani1191/GraphicalClustering
Project-URL: Bug Tracker, https://github.com/nmani1191/GraphicalClustering/issues
Classifier: Programming Language :: Python :: 3
Classifier: License :: OSI Approved :: MIT License
Classifier: Operating System :: OS Independent
Requires-Python: >=3.9
License-File: LICENSE
Requires-Dist: networkx (>=2.8.8)
Requires-Dist: pandas (>=1.5.2)
